scp_file_utils/__init__.py
scp_file_utils/console_helper.py
scp_file_utils/constants.py
scp_file_utils/download_file.py
scp_file_utils/file_utils.py
scp_file_utils/system_caller.py
scp_file_utils/conf/config.yaml
scp_file_utils-0.2.4.dist-info/AUTHORS.rst
scp_file_utils-0.2.4.dist-info/METADATA
scp_file_utils-0.2.4.dist-info/WHEEL
scp_file_utils-0.2.4.dist-info/entry_points.txt
scp_file_utils-0.2.4.dist-info/top_level.txt
scp_file_utils-0.2.4.dist-info/RECORD
